Remote_Sensing_Analysis/ImageProcessor.py
Remote_Sensing_Analysis/ImageTextAnalytics.py
Remote_Sensing_Analysis/ImageToTextConverter.py
Remote_Sensing_Analysis/YOLOInference.py
Remote_Sensing_Analysis/__init__.py
Remote_Sensing_Analysis/enhance_imagery.py
Remote_Sensing_Analysis-0.1.2.dist-info/LICENSE
Remote_Sensing_Analysis-0.1.2.dist-info/METADATA
Remote_Sensing_Analysis-0.1.2.dist-info/WHEEL
Remote_Sensing_Analysis-0.1.2.dist-info/top_level.txt
Remote_Sensing_Analysis-0.1.2.dist-info/RECORD
