Metadata-Version: 2.1
Name: Remote_Sensing_Analysis
Version: 0.1.2
Summary: Library that conducts analysis on Satellite Imagery
Home-page: http://github.com/aiden200/Remote_Sensing_Analysis
Author: Aiden Chang
Author-email: aidenchang@gmail.com
License: MIT
Keywords: Machine-Learning Remote-Sensing Object-detection
Requires-Python: >=3.9
License-File: LICENSE
Requires-Dist: pillow ==10.3.0
Requires-Dist: ultralytics ==8.2.2
Requires-Dist: transformers ==4.40.0
Requires-Dist: sentence-transformers ==2.7.0
Requires-Dist: sentencepiece ==0.2.0
Requires-Dist: timm ==0.9.16
